{
  "words": [
    {
      "word": "θορυβώδης",
      "example_el": "Οι γαλοπούλες στη φάρμα του παππού μου είναι πολύ θορυβώδης, ανυπομονώ να φαγωθούν.",
      "example_en": "The turkeys in my grandfather's farm are very noisy, I can't wait for them to get eaten."
    },
    {
      "word": "γερή",
      "example_el": "Αυτός έχει γερή μνήμη.",
      "example_en": "He has a good memory."
    },
    {
      "word": "διαγράψτε",
      "example_el": "Παρακαλώ διαγράψτε αυτή την ανάρτηση.",
      "example_en": "Please delete this post."
    },
    {
      "word": "φίλησαν",
      "example_el": "Ο Τομ και η Μαίρη φίλησαν ο ένας τον άλλο με πάθος.",
      "example_en": "Tom and Mary passionately kissed each other."
    },
    {
      "word": "υιοθετήσει",
      "example_el": "Αυτή η ορφανή αγγλική πρόταση μεταφράστηκε στο Tatoeba σε 14 γλώσσες, αλλά ο μεταφραστής δεν μπόρεσε να την υιοθετήσει επειδή δεν είναι μητρική αγγλική γλώσσα.",
      "example_en": "This orphaned English sentence was translated on Tatoeba into 14 languages, but the translator could not adopt it because he is not a native English speaker."
    }
  ]
}