{
  "words": [
    {
      "word": "κρέμεται",
      "example_el": "Το ημερολόγιο κρέμεται στον τοίχο.",
      "example_en": "The calendar hangs on the wall."
    },
    {
      "word": "πληρώσει",
      "example_el": "Έφυγε από το εστιατόριο χωρίς να πληρώσει.",
      "example_en": "He left the restaurant without paying."
    },
    {
      "word": "τουλίπες",
      "example_el": "Αυτή η πεδιάδα είναι γεμάτη τουλίπες, παπαρούνες και τριαντάφυλλα.",
      "example_en": "This plain is full of tulips, poppies, and roses."
    },
    {
      "word": "γρασίδι",
      "example_el": "Ας κάτσουμε εδώ στο γρασίδι.",
      "example_en": "Let's sit here on the grass."
    },
    {
      "word": "μεταφράσεις",
      "example_el": "Μπορείς να το μεταφράσεις μόνος σου;",
      "example_en": "Can you translate it on your own?"
    }
  ]
}